arlingo/__init__.py
arlingo/utilities.py
arlingo-0.3.59.dist-info/LICENSE
arlingo-0.3.59.dist-info/METADATA
arlingo-0.3.59.dist-info/WHEEL
arlingo-0.3.59.dist-info/top_level.txt
arlingo-0.3.59.dist-info/RECORD
