Metadata-Version: 2.1
Name: arlingo
Version: 0.3.59
License-File: LICENSE
Requires-Dist: beautifulsoup4
Requires-Dist: easygoogletranslate
Requires-Dist: gtts
Requires-Dist: pydub
Requires-Dist: clipboard
Requires-Dist: selenium
